Metadata-Version: 2.1
Name: concatrim
Version: 1.0.3
Summary: Python program to trim-then-concatenate A/V media files using ffmpeg
Home-page: https://github.com/keighrim/concatrim
Author: Keigh Rim
Author-email: krim@brandeis.edu
License: MIT
Platform: UNKNOWN
Requires-Python: >=3
